{"contributors": null, "truncated": false, "text": "RT @multishow: Momento emocionante!! \ud83d\ude0d \ud83d\ude0d \ud83d\ude0d   \n\ud83c\udfb6 \"I will love you unconditionally\" \ud83c\udfb6\n#KatyPerryNoMultishow\n http://t.co/t5tBJecN2n", "is_quote_status": false, "in_reply_to_status_id": null, "id": 648648380919496704, "favorite_count": 0, "source": "<a href=\"http://twitter.com/download/android\" rel=\"nofollow\">Twitter for Android</a>", "retweeted": false, "coordinates": null, "entities": {"symbols": [], "user_mentions": [{"id": 9604032, "indices": [3, 13], "id_str": "9604032", "screen_name": "multishow", "name": "Multishow"}], "hashtags": [{"indices": [84, 105], "text": "KatyPerryNoMultishow"}], "urls": [{"url": "http://t.co/t5tBJecN2n", "indices": [107, 129], "expanded_url": "http://bit.ly/1NWdbuY", "display_url": "bit.ly/1NWdbuY"}]}, "in_reply_to_screen_name": null, "in_reply_to_user_id": null, "retweet_count": 809, "id_str": "648648380919496704", "favorited": false, "retweeted_status": {"contributors": null, "truncated": false, "text": "Momento emocionante!! \ud83d\ude0d \ud83d\ude0d \ud83d\ude0d   \n\ud83c\udfb6 \"I will love you unconditionally\" \ud83c\udfb6\n#KatyPerryNoMultishow\n http://t.co/t5tBJecN2n", "is_quote_status": false, "in_reply_to_status_id": null, "id": 648356127936131072, "favorite_count": 866, "source": "<a href=\"http://snappytv.com\" rel=\"nofollow\">SnappyTV.com</a>", "retweeted": false, "coordinates": null, "entities": {"symbols": [], "user_mentions": [], "hashtags": [{"indices": [69, 90], "text": "KatyPerryNoMultishow"}], "urls": [{"url": "http://t.co/t5tBJecN2n", "indices": [92, 114], "expanded_url": "http://bit.ly/1NWdbuY", "display_url": "bit.ly/1NWdbuY"}]}, "in_reply_to_screen_name": null, "in_reply_to_user_id": null, "retweet_count": 809, "id_str": "648356127936131072", "favorited": false, "user": {"follow_request_sent": false, "has_extended_profile": false, "profile_use_background_image": true, "default_profile_image": false, "id": 9604032, "profile_background_image_url_https": "https://pbs.twimg.com/profile_background_images/432931611919654913/eEEL_yFg.jpeg", "verified": true, "profile_text_color": "383838", "profile_image_url_https": "https://pbs.twimg.com/profile_images/648952767709618176/HRvzE3Ub_normal.jpg", "profile_sidebar_fill_color": "FCFCFC", "entities": {"url": {"urls": [{"url": "http://t.co/EEqC2nyj8O", "indices": [0, 22], "expanded_url": "http://www.multishow.com.br", "display_url": "multishow.com.br"}]}, "description": {"urls": []}}, "followers_count": 3232289, "profile_sidebar_border_color": "FFFFFF", "id_str": "9604032", "profile_background_color": "7461A3", "listed_count": 4595, "is_translation_enabled": false, "utc_offset": -10800, "statuses_count": 140229, "description": "A vida sem roteiro. Siga tamb\u00e9m @canalbis, @canaloff e @tvzmultishow.", "friends_count": 92350, "location": "Brasil", "profile_link_color": "E65043", "profile_image_url": "http://pbs.twimg.com/profile_images/648952767709618176/HRvzE3Ub_normal.jpg", "following": false, "geo_enabled": true, "profile_banner_url": "https://pbs.twimg.com/profile_banners/9604032/1443416982", "profile_background_image_url": "http://pbs.twimg.com/profile_background_images/432931611919654913/eEEL_yFg.jpeg", "screen_name": "multishow", "lang": "en", "profile_background_tile": false, "favourites_count": 1131, "name": "Multishow", "notifications": false, "url": "http://t.co/EEqC2nyj8O", "created_at": "Mon Oct 22 19:08:06 +0000 2007", "contributors_enabled": false, "time_zone": "Brasilia", "protected": false, "default_profile": false, "is_translator": false}, "geo": null, "in_reply_to_user_id_str": null, "possibly_sensitive": false, "lang": "en", "created_at": "Mon Sep 28 04:38:41 +0000 2015", "in_reply_to_status_id_str": null, "place": null, "metadata": {"iso_language_code": "en", "result_type": "recent"}}, "user": {"follow_request_sent": false, "has_extended_profile": false, "profile_use_background_image": true, "default_profile_image": false, "id": 153193084, "profile_background_image_url_https": "https://pbs.twimg.com/profile_background_images/565706093888671744/0WlTOlmz.jpeg", "verified": false, "profile_text_color": "333333", "profile_image_url_https": "https://pbs.twimg.com/profile_images/645263224108122112/7U85hLUt_normal.jpg", "profile_sidebar_fill_color": "E6F6F9", "entities": {"description": {"urls": [{"url": "http://t.co/XzH0yeYU2l", "indices": [23, 45], "expanded_url": "http://nonsenseonyourmind.tumblr.com", "display_url": "nonsenseonyourmind.tumblr.com"}]}}, "followers_count": 546, "profile_sidebar_border_color": "FFFFFF", "id_str": "153193084", "profile_background_color": "131516", "listed_count": 2, "is_translation_enabled": false, "utc_offset": -10800, "statuses_count": 43643, "description": "gay things around here http://t.co/XzH0yeYU2l", "friends_count": 609, "location": "", "profile_link_color": "009999", "profile_image_url": "http://pbs.twimg.com/profile_images/645263224108122112/7U85hLUt_normal.jpg", "following": false, "geo_enabled": false, "profile_banner_url": "https://pbs.twimg.com/profile_banners/153193084/1444225222", "profile_background_image_url": "http://pbs.twimg.com/profile_background_images/565706093888671744/0WlTOlmz.jpeg", "screen_name": "Evrlastinglove_", "lang": "pt", "profile_background_tile": true, "favourites_count": 13013, "name": "sarah", "notifications": false, "url": null, "created_at": "Mon Jun 07 22:55:45 +0000 2010", "contributors_enabled": false, "time_zone": "Brasilia", "protected": false, "default_profile": false, "is_translator": false}, "geo": null, "in_reply_to_user_id_str": null, "possibly_sensitive": false, "lang": "en", "created_at": "Mon Sep 28 23:59:59 +0000 2015", "in_reply_to_status_id_str": null, "place": null, "metadata": {"iso_language_code": "en", "result_type": "recent"}}