{"contributors": null, "truncated": false, "text": "RT @ClaytonMFrazier: Surprise, I found this place in #washingtondc https://t.co/GctagOOVY3", "is_quote_status": false, "in_reply_to_status_id": null, "id": 648648381015920640, "favorite_count": 0, "source": "<a href=\"https://roundteam.co\" rel=\"nofollow\">RoundTeam</a>", "retweeted": false, "coordinates": null, "entities": {"symbols": [], "user_mentions": [{"id": 444159558, "indices": [3, 19], "id_str": "444159558", "screen_name": "ClaytonMFrazier", "name": "Clayton M Frazier"}], "hashtags": [{"indices": [53, 66], "text": "washingtondc"}], "urls": [{"url": "https://t.co/GctagOOVY3", "indices": [67, 90], "expanded_url": "https://youtu.be/DfVAAQVWUS8", "display_url": "youtu.be/DfVAAQVWUS8"}]}, "in_reply_to_screen_name": null, "in_reply_to_user_id": null, "retweet_count": 1, "id_str": "648648381015920640", "favorited": false, "retweeted_status": {"contributors": null, "truncated": false, "text": "Surprise, I found this place in #washingtondc https://t.co/GctagOOVY3", "is_quote_status": false, "in_reply_to_status_id": null, "id": 648632328445669376, "favorite_count": 1, "source": "<a href=\"http://twitter.com\" rel=\"nofollow\">Twitter Web Client</a>", "retweeted": false, "coordinates": null, "entities": {"symbols": [], "user_mentions": [], "hashtags": [{"indices": [32, 45], "text": "washingtondc"}], "urls": [{"url": "https://t.co/GctagOOVY3", "indices": [46, 69], "expanded_url": "https://youtu.be/DfVAAQVWUS8", "display_url": "youtu.be/DfVAAQVWUS8"}]}, "in_reply_to_screen_name": null, "in_reply_to_user_id": null, "retweet_count": 1, "id_str": "648632328445669376", "favorited": false, "user": {"follow_request_sent": false, "has_extended_profile": false, "profile_use_background_image": false, "default_profile_image": false, "id": 444159558, "profile_background_image_url_https": "https://abs.twimg.com/images/themes/theme15/bg.png", "verified": false, "profile_text_color": "000000", "profile_image_url_https": "https://pbs.twimg.com/profile_images/572973679874686976/-aLFMtUd_normal.jpeg", "profile_sidebar_fill_color": "000000", "entities": {"url": {"urls": [{"url": "https://t.co/nAsMvkMIM7", "indices": [0, 23], "expanded_url": "https://www.youtube.com/channel/UCCwxDK39IqpXo7z523AkAPA", "display_url": "youtube.com/channel/UCCwxD\u2026"}]}, "description": {"urls": []}}, "followers_count": 335, "profile_sidebar_border_color": "000000", "id_str": "444159558", "profile_background_color": "000000", "listed_count": 8, "is_translation_enabled": false, "utc_offset": null, "statuses_count": 483, "description": "YouTuber.", "friends_count": 380, "location": "", "profile_link_color": "0084B4", "profile_image_url": "http://pbs.twimg.com/profile_images/572973679874686976/-aLFMtUd_normal.jpeg", "following": false, "geo_enabled": false, "profile_banner_url": "https://pbs.twimg.com/profile_banners/444159558/1432178841", "profile_background_image_url": "http://abs.twimg.com/images/themes/theme15/bg.png", "screen_name": "ClaytonMFrazier", "lang": "en", "profile_background_tile": false, "favourites_count": 324, "name": "Clayton M Frazier", "notifications": false, "url": "https://t.co/nAsMvkMIM7", "created_at": "Thu Dec 22 23:45:46 +0000 2011", "contributors_enabled": false, "time_zone": null, "protected": false, "default_profile": false, "is_translator": false}, "geo": null, "in_reply_to_user_id_str": null, "possibly_sensitive": false, "lang": "en", "created_at": "Mon Sep 28 22:56:12 +0000 2015", "in_reply_to_status_id_str": null, "place": null, "metadata": {"iso_language_code": "en", "result_type": "recent"}}, "user": {"follow_request_sent": false, "has_extended_profile": false, "profile_use_background_image": false, "default_profile_image": false, "id": 1666311042, "profile_background_image_url_https": "https://abs.twimg.com/images/themes/theme2/bg.gif", "verified": false, "profile_text_color": "000000", "profile_image_url_https": "https://pbs.twimg.com/profile_images/598779998791671808/XnspL9B6_normal.jpg", "profile_sidebar_fill_color": "000000", "entities": {"description": {"urls": []}}, "followers_count": 234, "profile_sidebar_border_color": "000000", "id_str": "1666311042", "profile_background_color": "000000", "listed_count": 154, "is_translation_enabled": false, "utc_offset": -25200, "statuses_count": 5978, "description": "Washington DC - The capital of the greatest country on Earth!", "friends_count": 233, "location": "Washington, DC", "profile_link_color": "9266CC", "profile_image_url": "http://pbs.twimg.com/profile_images/598779998791671808/XnspL9B6_normal.jpg", "following": false, "geo_enabled": false, "profile_banner_url": "https://pbs.twimg.com/profile_banners/1666311042/1431595466", "profile_background_image_url": "http://abs.twimg.com/images/themes/theme2/bg.gif", "screen_name": "LuvWashingtonDC", "lang": "en", "profile_background_tile": false, "favourites_count": 0, "name": "Washington DC Lover", "notifications": false, "url": null, "created_at": "Tue Aug 13 00:21:49 +0000 2013", "contributors_enabled": false, "time_zone": "Pacific Time (US & Canada)", "protected": false, "default_profile": false, "is_translator": false}, "geo": null, "in_reply_to_user_id_str": null, "possibly_sensitive": false, "lang": "en", "created_at": "Mon Sep 28 23:59:59 +0000 2015", "in_reply_to_status_id_str": null, "place": null, "metadata": {"iso_language_code": "en", "result_type": "recent"}}