{"contributors": null, "truncated": false, "text": "RT @HowToGetAwayABC: The jaw-dropping moments only get bigger on an all-new #HTGAWM episode tonight at 10|9c! https://t.co/KRNF6IAhVO", "is_quote_status": false, "in_reply_to_status_id": null, "id": 649735544407109632, "favorite_count": 0, "source": "<a href=\"http://twitter.com/download/iphone\" rel=\"nofollow\">Twitter for iPhone</a>", "retweeted": false, "coordinates": null, "entities": {"symbols": [], "user_mentions": [{"id": 2463499796, "indices": [3, 19], "id_str": "2463499796", "screen_name": "HowToGetAwayABC", "name": "How To Get Away ABC"}], "hashtags": [{"indices": [76, 83], "text": "HTGAWM"}], "urls": [{"url": "https://t.co/KRNF6IAhVO", "indices": [110, 133], "expanded_url": "https://amp.twimg.com/v/cd1ce78a-3833-461f-a4ed-9d287092cc24", "display_url": "amp.twimg.com/v/cd1ce78a-383\u2026"}]}, "in_reply_to_screen_name": null, "in_reply_to_user_id": null, "retweet_count": 3288, "id_str": "649735544407109632", "favorited": false, "retweeted_status": {"contributors": null, "truncated": false, "text": "The jaw-dropping moments only get bigger on an all-new #HTGAWM episode tonight at 10|9c! https://t.co/KRNF6IAhVO", "is_quote_status": false, "in_reply_to_status_id": null, "id": 649546814627184640, "favorite_count": 5384, "source": "<a href=\"http://www.sprinklr.com\" rel=\"nofollow\">Sprinklr</a>", "retweeted": false, "coordinates": null, "entities": {"symbols": [], "user_mentions": [], "hashtags": [{"indices": [55, 62], "text": "HTGAWM"}], "urls": [{"url": "https://t.co/KRNF6IAhVO", "indices": [89, 112], "expanded_url": "https://amp.twimg.com/v/cd1ce78a-3833-461f-a4ed-9d287092cc24", "display_url": "amp.twimg.com/v/cd1ce78a-383\u2026"}]}, "in_reply_to_screen_name": null, "in_reply_to_user_id": null, "retweet_count": 3288, "id_str": "649546814627184640", "favorited": false, "user": {"follow_request_sent": false, "has_extended_profile": false, "profile_use_background_image": true, "default_profile_image": false, "id": 2463499796, "profile_background_image_url_https": "https://pbs.twimg.com/profile_background_images/515253245803900930/gHLh5Db-.jpeg", "verified": true, "profile_text_color": "333333", "profile_image_url_https": "https://pbs.twimg.com/profile_images/633758059832066048/Nm05H3Fz_normal.jpg", "profile_sidebar_fill_color": "DDEEF6", "entities": {"url": {"urls": [{"url": "http://t.co/0VEcE0bSVD", "indices": [0, 22], "expanded_url": "http://abc.go.com/shows/how-to-get-away-with-murder", "display_url": "abc.go.com/shows/how-to-g\u2026"}]}, "description": {"urls": []}}, "followers_count": 244052, "profile_sidebar_border_color": "000000", "id_str": "2463499796", "profile_background_color": "131516", "listed_count": 986, "is_translation_enabled": false, "utc_offset": null, "statuses_count": 10427, "description": "The official Twitter for ABC's How To Get Away With Murder. Watch Thursdays at 10|9c on ABC.", "friends_count": 157, "location": "", "profile_link_color": "DD2E44", "profile_image_url": "http://pbs.twimg.com/profile_images/633758059832066048/Nm05H3Fz_normal.jpg", "following": false, "geo_enabled": false, "profile_banner_url": "https://pbs.twimg.com/profile_banners/2463499796/1443164614", "profile_background_image_url": "http://pbs.twimg.com/profile_background_images/515253245803900930/gHLh5Db-.jpeg", "screen_name": "HowToGetAwayABC", "lang": "en", "profile_background_tile": false, "favourites_count": 481, "name": "How To Get Away ABC", "notifications": false, "url": "http://t.co/0VEcE0bSVD", "created_at": "Fri Apr 25 17:30:17 +0000 2014", "contributors_enabled": false, "time_zone": null, "protected": false, "default_profile": false, "is_translator": false}, "geo": null, "in_reply_to_user_id_str": null, "possibly_sensitive": false, "lang": "en", "created_at": "Thu Oct 01 11:30:03 +0000 2015", "in_reply_to_status_id_str": null, "place": null, "metadata": {"iso_language_code": "en", "result_type": "recent"}}, "user": {"follow_request_sent": false, "has_extended_profile": true, "profile_use_background_image": true, "default_profile_image": false, "id": 110242957, "profile_background_image_url_https": "https://pbs.twimg.com/profile_background_images/330240541/6a00e54f900c388833011278f89cb828a4-500wi.jpg", "verified": false, "profile_text_color": "333333", "profile_image_url_https": "https://pbs.twimg.com/profile_images/644562258249449472/d3963HfG_normal.jpg", "profile_sidebar_fill_color": "D9203F", "entities": {"description": {"urls": []}}, "followers_count": 2429, "profile_sidebar_border_color": "FFF8AD", "id_str": "110242957", "profile_background_color": "0F0E02", "listed_count": 11, "is_translation_enabled": false, "utc_offset": -28800, "statuses_count": 134236, "description": "yooooo, who is this nikka?", "friends_count": 1202, "location": "#seeul8trsyd", "profile_link_color": "163540", "profile_image_url": "http://pbs.twimg.com/profile_images/644562258249449472/d3963HfG_normal.jpg", "following": false, "geo_enabled": true, "profile_banner_url": "https://pbs.twimg.com/profile_banners/110242957/1444232781", "profile_background_image_url": "http://pbs.twimg.com/profile_background_images/330240541/6a00e54f900c388833011278f89cb828a4-500wi.jpg", "screen_name": "CaliforAnia", "lang": "en", "profile_background_tile": false, "favourites_count": 22236, "name": "13", "notifications": false, "url": null, "created_at": "Sun Jan 31 21:43:30 +0000 2010", "contributors_enabled": false, "time_zone": "Alaska", "protected": false, "default_profile": false, "is_translator": false}, "geo": null, "in_reply_to_user_id_str": null, "possibly_sensitive": false, "lang": "en", "created_at": "Thu Oct 01 23:59:59 +0000 2015", "in_reply_to_status_id_str": null, "place": null, "metadata": {"iso_language_code": "en", "result_type": "recent"}}