{"contributors": null, "truncated": false, "text": "RT @branthansen: In NYC. There are 80,000 restaurants here. ...and this is the line for @ChickfilA. http://t.co/DKD89lii3W", "is_quote_status": false, "in_reply_to_status_id": null, "id": 650460320243146753, "favorite_count": 0, "source": "<a href=\"http://twitter.com/download/iphone\" rel=\"nofollow\">Twitter for iPhone</a>", "retweeted": false, "coordinates": null, "entities": {"symbols": [], "user_mentions": [{"id": 15590648, "indices": [3, 15], "id_str": "15590648", "screen_name": "branthansen", "name": "Brant Hansen"}, {"id": 16043308, "indices": [88, 98], "id_str": "16043308", "screen_name": "ChickfilA", "name": "Chick-fil-A, Inc."}], "hashtags": [], "urls": [], "media": [{"source_user_id": 15590648, "source_status_id_str": "650371085767192580", "expanded_url": "http://twitter.com/branthansen/status/650371085767192580/video/1", "display_url": "pic.twitter.com/DKD89lii3W", "url": "http://t.co/DKD89lii3W", "media_url_https": "https://pbs.twimg.com/ext_tw_video_thumb/650371008449380356/pu/img/gHxA_m1rnuLVGOzr.jpg", "source_user_id_str": "15590648", "source_status_id": 650371085767192580, "id_str": "650371008449380356", "sizes": {"small": {"h": 191, "resize": "fit", "w": 340}, "large": {"h": 576, "resize": "fit", "w": 1024}, "medium": {"h": 338, "resize": "fit", "w": 600}, "thumb": {"h": 150, "resize": "crop", "w": 150}}, "indices": [100, 122], "type": "photo", "id": 650371008449380356, "media_url": "http://pbs.twimg.com/ext_tw_video_thumb/650371008449380356/pu/img/gHxA_m1rnuLVGOzr.jpg"}]}, "in_reply_to_screen_name": null, "in_reply_to_user_id": null, "retweet_count": 692, "id_str": "650460320243146753", "favorited": false, "retweeted_status": {"contributors": null, "truncated": false, "text": "In NYC. There are 80,000 restaurants here. ...and this is the line for @ChickfilA. http://t.co/DKD89lii3W", "is_quote_status": false, "in_reply_to_status_id": null, "id": 650371085767192580, "favorite_count": 594, "source": "<a href=\"http://twitter.com/download/iphone\" rel=\"nofollow\">Twitter for iPhone</a>", "retweeted": false, "coordinates": null, "entities": {"symbols": [], "user_mentions": [{"id": 16043308, "indices": [71, 81], "id_str": "16043308", "screen_name": "ChickfilA", "name": "Chick-fil-A, Inc."}], "hashtags": [], "urls": [], "media": [{"expanded_url": "http://twitter.com/branthansen/status/650371085767192580/video/1", "display_url": "pic.twitter.com/DKD89lii3W", "url": "http://t.co/DKD89lii3W", "media_url_https": "https://pbs.twimg.com/ext_tw_video_thumb/650371008449380356/pu/img/gHxA_m1rnuLVGOzr.jpg", "id_str": "650371008449380356", "sizes": {"small": {"h": 191, "resize": "fit", "w": 340}, "large": {"h": 576, "resize": "fit", "w": 1024}, "medium": {"h": 338, "resize": "fit", "w": 600}, "thumb": {"h": 150, "resize": "crop", "w": 150}}, "indices": [83, 105], "type": "photo", "id": 650371008449380356, "media_url": "http://pbs.twimg.com/ext_tw_video_thumb/650371008449380356/pu/img/gHxA_m1rnuLVGOzr.jpg"}]}, "in_reply_to_screen_name": null, "in_reply_to_user_id": null, "retweet_count": 692, "id_str": "650371085767192580", "favorited": false, "user": {"follow_request_sent": false, "has_extended_profile": false, "profile_use_background_image": true, "default_profile_image": false, "id": 15590648, "profile_background_image_url_https": "https://pbs.twimg.com/profile_background_images/431925908711034881/DRqHR51a.jpeg", "verified": false, "profile_text_color": "3E4415", "profile_image_url_https": "https://pbs.twimg.com/profile_images/639868746798993408/X_XHButi_normal.jpg", "profile_sidebar_fill_color": "99CC33", "entities": {"url": {"urls": [{"url": "http://t.co/fMxP2AkVCJ", "indices": [0, 22], "expanded_url": "http://www.branthansen.com", "display_url": "branthansen.com"}]}, "description": {"urls": [{"url": "http://t.co/Go1GHupz0E", "indices": [40, 62], "expanded_url": "http://amzn.to/WF7R85", "display_url": "amzn.to/WF7R85"}]}}, "followers_count": 19608, "profile_sidebar_border_color": "FFFFFF", "id_str": "15590648", "profile_background_color": "FFFFFF", "listed_count": 246, "is_translation_enabled": false, "utc_offset": -14400, "statuses_count": 9573, "description": "Global Nerd of Intrigue. I'm an author (http://t.co/Go1GHupz0E) and do radio, too. I work for the beautiful and amazing @cureintl.", "friends_count": 9046, "location": "cure.org", "profile_link_color": "0A0F47", "profile_image_url": "http://pbs.twimg.com/profile_images/639868746798993408/X_XHButi_normal.jpg", "following": false, "geo_enabled": false, "profile_banner_url": "https://pbs.twimg.com/profile_banners/15590648/1443016530", "profile_background_image_url": "http://pbs.twimg.com/profile_background_images/431925908711034881/DRqHR51a.jpeg", "screen_name": "branthansen", "lang": "en", "profile_background_tile": false, "favourites_count": 9065, "name": "Brant Hansen", "notifications": false, "url": "http://t.co/fMxP2AkVCJ", "created_at": "Thu Jul 24 23:11:52 +0000 2008", "contributors_enabled": false, "time_zone": "Eastern Time (US & Canada)", "protected": false, "default_profile": false, "is_translator": false}, "geo": null, "in_reply_to_user_id_str": null, "possibly_sensitive": false, "lang": "en", "created_at": "Sat Oct 03 18:05:24 +0000 2015", "in_reply_to_status_id_str": null, "place": null, "metadata": {"iso_language_code": "en", "result_type": "recent"}}, "user": {"follow_request_sent": false, "has_extended_profile": true, "profile_use_background_image": true, "default_profile_image": false, "id": 709609681, "profile_background_image_url_https": "https://abs.twimg.com/images/themes/theme1/bg.png", "verified": false, "profile_text_color": "333333", "profile_image_url_https": "https://pbs.twimg.com/profile_images/645720623436558337/tv_kejiT_normal.jpg", "profile_sidebar_fill_color": "DDEEF6", "entities": {"url": {"urls": [{"url": "http://t.co/1FAcsxxO7M", "indices": [0, 22], "expanded_url": "http://barackandmichelle.com", "display_url": "barackandmichelle.com"}]}, "description": {"urls": [{"url": "http://t.co/X57PGHWnX3", "indices": [72, 94], "expanded_url": "http://smarturl.it/iWDYM", "display_url": "smarturl.it/iWDYM"}]}}, "followers_count": 865, "profile_sidebar_border_color": "C0DEED", "id_str": "709609681", "profile_background_color": "C0DEED", "listed_count": 7, "is_translation_enabled": false, "utc_offset": null, "statuses_count": 40513, "description": "justin drew bieber || BUY 'WHAT DO YOU MEAN' BY JUSTIN BIEBER ON ITUNES http://t.co/X57PGHWnX3", "friends_count": 265, "location": "California, USA", "profile_link_color": "0084B4", "profile_image_url": "http://pbs.twimg.com/profile_images/645720623436558337/tv_kejiT_normal.jpg", "following": false, "geo_enabled": true, "profile_banner_url": "https://pbs.twimg.com/profile_banners/709609681/1443305580", "profile_background_image_url": "http://abs.twimg.com/images/themes/theme1/bg.png", "screen_name": "DeniseBriceno", "lang": "en", "profile_background_tile": false, "favourites_count": 15183, "name": "purpose", "notifications": false, "url": "http://t.co/1FAcsxxO7M", "created_at": "Sat Jul 21 21:34:40 +0000 2012", "contributors_enabled": false, "time_zone": null, "protected": false, "default_profile": true, "is_translator": false}, "geo": null, "in_reply_to_user_id_str": null, "possibly_sensitive": false, "lang": "en", "created_at": "Sat Oct 03 23:59:59 +0000 2015", "in_reply_to_status_id_str": null, "place": null, "metadata": {"iso_language_code": "en", "result_type": "recent"}}