{"contributors": null, "truncated": false, "text": "RT @BobOngQuotes: Sometimes, just a hug will do. No need for advice.", "is_quote_status": false, "in_reply_to_status_id": null, "id": 650822708133933056, "favorite_count": 0, "source": "<a href=\"http://twitter.com/download/android\" rel=\"nofollow\">Twitter for Android</a>", "retweeted": false, "coordinates": null, "entities": {"symbols": [], "user_mentions": [{"id": 954995377, "indices": [3, 16], "id_str": "954995377", "screen_name": "BobOngQuotes", "name": "Bob Ong"}], "hashtags": [], "urls": []}, "in_reply_to_screen_name": null, "in_reply_to_user_id": null, "retweet_count": 247, "id_str": "650822708133933056", "favorited": false, "retweeted_status": {"contributors": null, "truncated": false, "text": "Sometimes, just a hug will do. No need for advice.", "is_quote_status": false, "in_reply_to_status_id": null, "id": 650817688755814400, "favorite_count": 183, "source": "<a href=\"https://about.twitter.com/products/tweetdeck\" rel=\"nofollow\">TweetDeck</a>", "retweeted": false, "coordinates": null, "entities": {"symbols": [], "user_mentions": [], "hashtags": [], "urls": []}, "in_reply_to_screen_name": null, "in_reply_to_user_id": null, "retweet_count": 247, "id_str": "650817688755814400", "favorited": false, "user": {"follow_request_sent": false, "has_extended_profile": false, "profile_use_background_image": false, "default_profile_image": false, "id": 954995377, "profile_background_image_url_https": "https://pbs.twimg.com/profile_background_images/378800000166264672/LRbbf4Bt.jpeg", "verified": false, "profile_text_color": "333333", "profile_image_url_https": "https://pbs.twimg.com/profile_images/542897851500466177/bYhZmW_j_normal.jpeg", "profile_sidebar_fill_color": "F3F3F3", "entities": {"description": {"urls": []}}, "followers_count": 824808, "profile_sidebar_border_color": "FFFFFF", "id_str": "954995377", "profile_background_color": "EBEBEB", "listed_count": 331, "is_translation_enabled": false, "utc_offset": -25200, "statuses_count": 104913, "description": "YOUR NO. 1 SOURCE OF BOB-ONG QUOTES! MEMBER: United Influencers", "friends_count": 145, "location": "{contactbobong@yahoo.com \u2709\ufe0f}", "profile_link_color": "1F98C7", "profile_image_url": "http://pbs.twimg.com/profile_images/542897851500466177/bYhZmW_j_normal.jpeg", "following": false, "geo_enabled": false, "profile_banner_url": "https://pbs.twimg.com/profile_banners/954995377/1413354234", "profile_background_image_url": "http://pbs.twimg.com/profile_background_images/378800000166264672/LRbbf4Bt.jpeg", "screen_name": "BobOngQuotes", "lang": "en", "profile_background_tile": false, "favourites_count": 35, "name": "Bob Ong", "notifications": false, "url": null, "created_at": "Sun Nov 18 06:56:50 +0000 2012", "contributors_enabled": false, "time_zone": "Pacific Time (US & Canada)", "protected": false, "default_profile": false, "is_translator": false}, "geo": null, "in_reply_to_user_id_str": null, "lang": "en", "created_at": "Sun Oct 04 23:40:03 +0000 2015", "in_reply_to_status_id_str": null, "place": null, "metadata": {"iso_language_code": "en", "result_type": "recent"}}, "user": {"follow_request_sent": false, "has_extended_profile": true, "profile_use_background_image": false, "default_profile_image": false, "id": 3256334040, "profile_background_image_url_https": "https://abs.twimg.com/images/themes/theme1/bg.png", "verified": false, "profile_text_color": "000000", "profile_image_url_https": "https://pbs.twimg.com/profile_images/650165936998117376/v9xo0TNM_normal.jpg", "profile_sidebar_fill_color": "000000", "entities": {"description": {"urls": []}}, "followers_count": 331, "profile_sidebar_border_color": "000000", "id_str": "3256334040", "profile_background_color": "000000", "listed_count": 0, "is_translation_enabled": false, "utc_offset": -25200, "statuses_count": 17889, "description": "Crazy psycho bitch \u2022 Ram's pig.", "friends_count": 132, "location": "", "profile_link_color": "9266CC", "profile_image_url": "http://pbs.twimg.com/profile_images/650165936998117376/v9xo0TNM_normal.jpg", "following": false, "geo_enabled": true, "profile_banner_url": "https://pbs.twimg.com/profile_banners/3256334040/1444221854", "profile_background_image_url": "http://abs.twimg.com/images/themes/theme1/bg.png", "screen_name": "GarciaEllaaa", "lang": "en", "profile_background_tile": false, "favourites_count": 10492, "name": "abcdella", "notifications": false, "url": null, "created_at": "Fri Jun 26 07:10:50 +0000 2015", "contributors_enabled": false, "time_zone": "Pacific Time (US & Canada)", "protected": false, "default_profile": false, "is_translator": false}, "geo": null, "in_reply_to_user_id_str": null, "lang": "en", "created_at": "Sun Oct 04 23:59:59 +0000 2015", "in_reply_to_status_id_str": null, "place": null, "metadata": {"iso_language_code": "en", "result_type": "recent"}}